[{"line":1,"elements":[{"start_timestamp":"2023-05-31T15:54:58.930Z","line":3,"name":"Add a new Template to the manage templates field.","description":"","id":"add-templates;add-a-new-template-to-the-manage-templates-field.","type":"scenario","keyword":"Scenario","steps":[{"result":{"status":"undefined"},"line":4,"name":"User launch Chrome browser and Open the URL \"https://freezer-analytics.web.app\"","match":{},"keyword":"Given "},{"result":{"duration":1513900,"status":"skipped"},"line":5,"name":"Enter emailId and Password","match":{},"keyword":"And "},{"result":{"status":"skipped"},"line":6,"name":"Click on login btn","match":{},"keyword":"And "},{"result":{"status":"skipped"},"line":7,"name":"Verify dashboard page","match":{},"keyword":"Then "},{"result":{"duration":4149700,"status":"skipped"},"line":8,"name":"Go to the Manage Template section","match":{},"keyword":"Then "},{"result":{"status":"skipped"},"line":9,"name":"Click on Add Template","match":{},"keyword":"Then "},{"result":{"status":"skipped"},"line":10,"name":"Write a Template Name","match":{},"keyword":"And "},{"result":{"status":"skipped"},"line":11,"name":"Select type of Template","match":{},"keyword":"And "},{"result":{"status":"skipped"},"line":12,"name":"Click on Choose file for Upload image","match":{},"keyword":"And "},{"result":{"status":"skipped"},"line":13,"name":"Click on Submit btn","match":{},"keyword":"Then "},{"result":{"status":"skipped"},"line":14,"name":"Search the Template Name on Search field abd Verify in Table","match":{},"keyword":"Then "},{"result":{"status":"skipped"},"line":15,"name":"Click on View Template","match":{},"keyword":"And "},{"result":{"status":"skipped"},"line":16,"name":"Click on Edit Template","match":{},"keyword":"And "},{"result":{"status":"skipped"},"line":17,"name":"Click on Delete Template","match":{},"keyword":"And "},{"result":{"status":"skipped"},"line":18,"name":"Click on Logout","match":{},"keyword":"And "},{"result":{"duration":1081100,"status":"skipped"},"line":19,"name":"Driver close","match":{},"keyword":"Then "}]}],"name":"Add Templates","description":"","id":"add-templates","keyword":"Feature","uri":"file:Features/AddTemplate.feature","tags":[]}]